NiukeRenliziyuanGangQiuzhiJingyanFenxiang20212022/README.md
NiukeRenliziyuanGangQiuzhiJingyanFenxiang20212022/__init__.py
NiukeRenliziyuanGangQiuzhiJingyanFenxiang20212022/__main__.py
NiukeRenliziyuanGangQiuzhiJingyanFenxiang20212022/file.epub
NiukeRenliziyuanGangQiuzhiJingyanFenxiang20212022/index.html
NiukeRenliziyuanGangQiuzhiJingyanFenxiang20212022/css/__init__.py
NiukeRenliziyuanGangQiuzhiJingyanFenxiang20212022/css/annotations.css
NiukeRenliziyuanGangQiuzhiJingyanFenxiang20212022/css/main.css
NiukeRenliziyuanGangQiuzhiJingyanFenxiang20212022/css/normalize.css
NiukeRenliziyuanGangQiuzhiJingyanFenxiang20212022/css/popup.css
NiukeRenliziyuanGangQiuzhiJingyanFenxiang20212022/font/__init__.py
NiukeRenliziyuanGangQiuzhiJingyanFenxiang20212022/font/fontello.eot
NiukeRenliziyuanGangQiuzhiJingyanFenxiang20212022/font/fontello.svg
NiukeRenliziyuanGangQiuzhiJingyanFenxiang20212022/font/fontello.ttf
NiukeRenliziyuanGangQiuzhiJingyanFenxiang20212022/font/fontello.woff
NiukeRenliziyuanGangQiuzhiJingyanFenxiang20212022/img/__init__.py
NiukeRenliziyuanGangQiuzhiJingyanFenxiang20212022/img/annotator-glyph-sprite.png
NiukeRenliziyuanGangQiuzhiJingyanFenxiang20212022/img/annotator-icon-sprite.png
NiukeRenliziyuanGangQiuzhiJingyanFenxiang20212022/img/apple-touch-icon.png
NiukeRenliziyuanGangQiuzhiJingyanFenxiang20212022/img/cancelfullscreen.png
NiukeRenliziyuanGangQiuzhiJingyanFenxiang20212022/img/close.png
NiukeRenliziyuanGangQiuzhiJingyanFenxiang20212022/img/fullscreen.png
NiukeRenliziyuanGangQiuzhiJingyanFenxiang20212022/img/loader.gif
NiukeRenliziyuanGangQiuzhiJingyanFenxiang20212022/img/menu-icon.png
NiukeRenliziyuanGangQiuzhiJingyanFenxiang20212022/img/save.png
NiukeRenliziyuanGangQiuzhiJingyanFenxiang20212022/img/saved.png
NiukeRenliziyuanGangQiuzhiJingyanFenxiang20212022/img/settings-s.png
NiukeRenliziyuanGangQiuzhiJingyanFenxiang20212022/img/settings.png
NiukeRenliziyuanGangQiuzhiJingyanFenxiang20212022/img/star.png
niuke_renliziyuan_gang_qiuzhi_jingyan_fenxiang_2021_2022-2024.3.6.0.dist-info/METADATA
niuke_renliziyuan_gang_qiuzhi_jingyan_fenxiang_2021_2022-2024.3.6.0.dist-info/WHEEL
niuke_renliziyuan_gang_qiuzhi_jingyan_fenxiang_2021_2022-2024.3.6.0.dist-info/entry_points.txt
niuke_renliziyuan_gang_qiuzhi_jingyan_fenxiang_2021_2022-2024.3.6.0.dist-info/top_level.txt
niuke_renliziyuan_gang_qiuzhi_jingyan_fenxiang_2021_2022-2024.3.6.0.dist-info/RECORD
